README.md
setup.py
pymorm/__init__.py
pymorm/document.py
pymorm/mapped_manipulator.py
pymorm/mongo_object.py
pymorm/query.py
pymorm.egg-info/PKG-INFO
pymorm.egg-info/SOURCES.txt
pymorm.egg-info/dependency_links.txt
pymorm.egg-info/pbr.json
pymorm.egg-info/requires.txt
pymorm.egg-info/top_level.txt
pymorm.egg-info/zip-safe
test/test.py