Metadata-Version: 1.1
Name: pymorm
Version: 0.4.10
Summary: Really simple pymongo-based ODM
Home-page: https://github.com/devilicecream/pymorm
Author: Walter Danilo Galante
Author-email: walter.galante@proxtome.com
License: UNKNOWN
Keywords: mongodb pymongo simple odm orm mongo database
Platform: UNKNOWN
Classifier: Development Status :: 3 - Alpha
Classifier: License :: OSI Approved :: MIT License
Classifier: Programming Language :: Python
Classifier: Topic :: Database :: Front-Ends
Classifier: Topic :: Software Development :: Libraries :: Python Modules
Classifier: Intended Audience :: Developers
